gamcoach/__init__.py
gamcoach/counterfactuals.py
gamcoach/gamcoach.py
gamcoach-0.1.4.dist-info/LICENSE
gamcoach-0.1.4.dist-info/METADATA
gamcoach-0.1.4.dist-info/WHEEL
gamcoach-0.1.4.dist-info/top_level.txt
gamcoach-0.1.4.dist-info/RECORD
