Metadata-Version: 2.1
Name: gamcoach
Version: 0.1.4
Summary: Generating counterfactual explanations for GAMs
Home-page: https://github.com/xiaohk/gam-coach
Author: Jay Wang
Author-email: jay@zijie.wang
License: MIT license
Keywords: gamcoach
Classifier: Development Status :: 2 - Pre-Alpha
Classifier: Intended Audience :: Developers
Classifier: License :: OSI Approved :: MIT License
Classifier: Natural Language :: English
Classifier: Programming Language :: Python :: 3
Classifier: Programming Language :: Python :: 3.6
Classifier: Programming Language :: Python :: 3.7
Classifier: Programming Language :: Python :: 3.8
Requires-Python: >=3.6
License-File: LICENSE
Requires-Dist: interpret (>=0.3.0)
Requires-Dist: interpret-core (>=0.3.0)
Requires-Dist: pulp
